{
  "partition_plans": {
    "1": {
      "tables": {
        "warehouse": {
          "partitions": {
            "0": "1-2",
            "1": "2-3"
          }
        }      
      }
    },
    "2": {
      "tables": {
        "warehouse": {
          "partitions": {
            "1": "1-3"
          }
        }      
      }
    },
    "3": {
      "tables": {
        "warehouse": {
          "partitions": {
            "0": "1-3"
          }
        }      
      }
    },

  }, 
  "default_table": "warehouse"
}

